flashmemo/__init__.py
flashmemo/__main__.py
flashmemo/cli.py
flashmemo/core.py
flashmemo/html_export.py
flashmemo/storage.py
flashmemo/web.py
flashmemo/data/flashcards.json
flashmemo/data/lashcards.json
flashmemo/templates/add.html
flashmemo/templates/index.html
flashmemo/templates/quiz.html
flashmemo-0.1.0.dist-info/licenses/LICENSE
flashmemo-0.1.0.dist-info/METADATA
flashmemo-0.1.0.dist-info/WHEEL
flashmemo-0.1.0.dist-info/entry_points.txt
flashmemo-0.1.0.dist-info/top_level.txt
flashmemo-0.1.0.dist-info/RECORD
