Metadata-Version: 2.4
Name: flashmemo
Version: 0.1.0
Summary: Un outil CLI pour créer et réviser avec des cartes mémoire
Home-page: https://github.com/ton-compte/flashmemo
Author: Digital Dreamer
Author-email: digitaldreamer@gmail.com
License: MIT
Classifier: Programming Language :: Python :: 3
Classifier: License :: OSI Approved :: MIT License
Classifier: Operating System :: OS Independent
Requires-Python: >=3.7
License-File: LICENSE
Requires-Dist: Flask>=2.0
Dynamic: author
Dynamic: author-email
Dynamic: classifier
Dynamic: description
Dynamic: description-content-type
Dynamic: home-page
Dynamic: license
Dynamic: license-file
Dynamic: requires-dist
Dynamic: requires-python
Dynamic: summary
